MANIFEST.in
README.md
setup.py
./variables
pykonker/__init__.py
pykonker/__main__.py
pykonker.egg-info/PKG-INFO
pykonker.egg-info/SOURCES.txt
pykonker.egg-info/dependency_links.txt
pykonker.egg-info/requires.txt
pykonker.egg-info/top_level.txt
pykonker/main/__init__.py
pykonker/main/api.py
pykonker/main/parser.py