Metadata-Version: 2.1
Name: pykonker
Version: 1.4.2
Summary: provides a simple interface to connect, send and receive information from Konker REST API
Home-page: https://github.com/KonkerLabs/pykonker
Author: Alexandre Junqueira
Author-email: alexjunq@konkerlabs.com
License: UNKNOWN
Platform: UNKNOWN
Classifier: Operating System :: POSIX :: Linux
Classifier: License :: OSI Approved :: MIT License
Classifier: Programming Language :: Python :: 3.5
Classifier: Programming Language :: Python :: 3.6
Classifier: Programming Language :: Python :: 3.7
